{
  "w": 1538383850744,
  "n": "Небеса отражают славу Твою",
  "d": 5,
  "p": 11,
  "al": "1~20200701//164457_62_65.mp3",
  "t": [
    "Небеса отражают славу Твою\nИ творение - зеркало для Тебя.\nЯ величие, Боже, Твоё познаю,\nКогда я смотрю на Твои дела.",
    "О-о, как Ты прекрасен!\nКак Ты прекрасен, о Господь!\nО-о, как я люблю Тебя!\nКак я люблю Тебя, мой Иисус!",
    "Вся Вселенная славой Твоею полна,\nЗвёзды нам говорят о Тебе.\nЭтот мир созидает сила Твоя\nИ любовь открывает путь к Тебе."
  ],
  "c": ["Fm D# C#\nA#m D#\nFm D# C#\nA#m D#", "Fm G#\nA#m G#-D#\nFm G#\nA#m A#m/G Fm"],
  "o": [
    { "w": 4, "c": 0, "k": 15 },
    {
      "c": 0,
      "p": [
        [-1, 6, 13],
        [8, 12],
        [-1, 7, 15],
        [6, 11]
      ],
      "m": 1,
      "t": 0,
      "w": 0,
      "k": 39
    },
    {
      "c": 1,
      "p": [
        [0, 8],
        [5, 11],
        [0, 8],
        [5, 9, 14]
      ],
      "m": 1,
      "t": 1,
      "w": 1,
      "k": 94
    },
    {
      "c": 0,
      "p": [
        [-1, 7, 15],
        [7, 9],
        [-1, 7, 14],
        [7, 10]
      ],
      "t": 2,
      "w": 2,
      "k": 39
    },
    { "w": 3, "a": 1, "r": 2 }
  ]
}
