{
  "w": 1614755948210,
  "n": "Звёзды потускнеют",
  "p": 7,
  "al": "4~2016071016184168.mp3",
  "t": [
    "Звёзды потускнеют...\nНебо свернётся рулоном...\nСилы сильных ослабеют,\nИ все предстанут пред Его престолом.",
    "И Он взойдёт, как Солнце Правды,\nЗасияет над землёю.\nК кому-то станет Он лицом и даст награды,\nА к кому-то станет Он спиною.",
    "И тогда они заплачут горько,\nИ слёзы побегут рекою:\n\"Почему, Господь, Ты не со мною?\nПочему стоишь ко мне спиною?\".",
    "И Он ответит: \"А, ну-ка, вспомни,\nКогда в двери Я твои стучался,\nПомнишь? Ты стоял ко Мне спиною,\nХоть и знал, что Я в тебе нуждался\".",
    "И ты воскликнешь в стенании горьком:\n\"Покажи, когда Ты в дверь стучался?\nСкажи, когда Ты, Бог, во мне нуждался?\nНо оказался я тогда холодным\".",
    "\"Я был ребёнком, просящим хлеба,\nЯ был избит и стонал от боли,\nНо мимо ты прошёл, смотря на небо,\nПосыпая Мои раны солью\";",
    "\"Но те, кому Я раздаю награды,\nУслыхали плач - пришли на помощь.\nИсцеленью Моему были рады,\nОжидая, что и Я их вспомню...\"",
    "И войдут они в познание Бога,\nИ в одно сплошное наслаждение.\nА другие не заплатят своего долга,\nХоть и вечно будут жить в мученьях."
  ],
  "c": ["Am C\nDm Em Am\nAm C\nDm Em Am", "C-F C\nDm-Em Am\nF C Dm\nAm Em Am", "Am Em Am\nC F C\nF C Dm\nAm Em Am"],
  "o": [
    {
      "t": 0,
      "p": [
        [0, 5],
        [0, 4, 8],
        [0, 8],
        [2, 8, 14]
      ],
      "s": "thirdo",
      "m": 1,
      "c": 0,
      "w": 0
    },
    {
      "t": 1,
      "p": [
        [5, 12],
        [2, 8],
        [5, 11, 18],
        [4, 10, 13]
      ],
      "s": "+",
      "m": 1,
      "c": 1,
      "w": 1
    },
    {
      "t": 2,
      "p": [
        [3, 9, 12],
        [2, 7, 10],
        [3, 9, 13],
        [2, 9, 12]
      ],
      "s": " one",
      "m": 1,
      "c": 2,
      "w": 2
    },
    {
      "t": 3,
      "p": [
        [5, 10, 13],
        [4, 10, 13],
        [3, 10, 13],
        [4, 12, 15]
      ],
      "s": "one",
      "c": 2,
      "w": 3
    },
    {
      "t": 4,
      "p": [
        [5, 10, 14],
        [2, 10, 13],
        [4, 12, 15],
        [4, 10, 13]
      ],
      "s": " one",
      "c": 2,
      "w": 4
    },
    {
      "t": 5,
      "p": [
        [5, 9, 12],
        [5, 10, 14],
        [5, 11, 15],
        [2, 8, 11]
      ],
      "s": "one",
      "c": 2,
      "w": 5
    },
    {
      "t": 6,
      "p": [
        [5, 11, 14],
        [5, 9, 13],
        [2, 7, 12],
        [2, 9, 13]
      ],
      "s": " one",
      "c": 2,
      "w": 6
    },
    {
      "t": 7,
      "p": [
        [3, 10, 14],
        [4, 11, 12],
        [3, 9, 16],
        [4, 10, 14]
      ],
      "s": "one",
      "c": 2,
      "w": 7
    },
    { "a": 0, "w": 8 }
  ]
}
