{
  "w": 1623785109572,
  "n": "Будем радоваться, братья",
  "c": ["Cm A#\nG#7 G Cm\nCm A#\nG# G Cm", "G# D# Fm Gsus4-G\nG# D# Fm Gsus4-G\nCm A#\nG#7 G Cm"],
  "t": [
    "Будем радоваться, братья,\nпрочь уныние и страх -\nПринял нас Христос в объятья,\nи хранит в Своих руках.",
    "Братья, радуйтесь о Боге,\nо Его святых делах;\nИ с восторгом, без тревоги\nвоспевайте вы в сердцах.",
    "Прежде гибель нам всечасно\nздесь грозила на пути,\nНо Христос рукою властной\nнас призвал за Ним идти.",
    "Были в рубищах мы бедных,\nныне мы богаты в Нём,\nКруг сокровищ заповедных\nОн нам даст в краю Своём.",
    "Как слепые, в тьме греховной\nмы блуждали без путей;\nСвет небесный, свет духовный\nдал нам зренье для очей.",
    "Если скорби, искушенья\nпопустил бы нам Господь,\nВера сильна все сомненья\nи печаль в нас побороть.",
    "Пусть средь бед и испытанья\nв тайных помыслах сердец\nТвёрдо будет упованье:\nс нами Бог, благой Отец!",
    "Радость наша совершенна,\nот Христа, не от людей,\nИ ничто во всей Вселенной\nовладеть не может ей.",
    "ПРОИГРЫШ"
  ],
  "o": [
    { "w": 8, "c": 1, "k": 15 },
    {
      "w": 0,
      "p": [
        [3, 8],
        [3, 5, 9],
        [3, 11],
        [3, 7, 10]
      ],
      "c": 0,
      "t": 0,
      "k": -39
    },
    {
      "w": 1,
      "p": [
        [3, 5, 9, 10],
        [-2, 3, 6, 9],
        [4, 10],
        [2, 5, 9]
      ],
      "t": 1,
      "c": 1,
      "k": 81
    },
    {
      "w": 2,
      "p": [
        [3, 9],
        [3, 6, 9],
        [3, 10],
        [3, 7, 10]
      ],
      "c": 0,
      "t": 2,
      "k": 39
    },
    {
      "w": 3,
      "p": [
        [-2, 4, 6, 11],
        [-2, 3, 6, 10],
        [3, 8],
        [4, 8, 11]
      ],
      "t": 3,
      "c": 1,
      "k": 81
    },
    {
      "w": 4,
      "p": [
        [3, 10],
        [3, 6, 9],
        [3, 9],
        [4, 7, 10]
      ],
      "c": 0,
      "t": 4,
      "k": -39
    },
    {
      "w": 5,
      "p": [
        [-2, 3, 6, 8],
        [-2, 2, 6, 9],
        [3, 9],
        [3, 8, 10]
      ],
      "t": 5,
      "c": 1,
      "k": 81
    },
    { "w": 9, "c": 1, "k": 80 },
    {
      "w": 6,
      "p": [
        [4, 10],
        [4, 6, 9],
        [3, 8],
        [4, 7, 10]
      ],
      "c": 0,
      "t": 6,
      "k": 39
    },
    {
      "w": 7,
      "p": [
        [3, 6, 8, 9],
        [-2, 3, 7, 10],
        [3, 10],
        [2, 6, 9]
      ],
      "t": 7,
      "c": 1,
      "r": 2,
      "k": 81
    }
  ]
}
