{
  "w": 1640034261064,
  "n": "О наш Отец на небесах!",
  "c": ["Gm D\nD7 Gm\nA# F-D\nGm D Gm"],
  "t": [
    "О наш Отец на небесах!\nПрими моление моё:\nДа, славно в славных чудесах,\nСвятится имя ввек Твоё!",
    "Всеведущ Ты и всемогущ,\nТрепещет пред Тобою всё;\nВсевидящ Ты и вездесущ,\nДа придёт царствие Твоё.",
    "Премудрости Ты, Боже, полн,\nИ в счастье мысль одна моя:\nПусть средь житейских бурь и волн\nДа будет воля ввек Твоя!",
    "Ты милосерд, Ты справедлив;\nОставь долги Ты наши нам,\nКак, гнев и злобу позабыв,\nПрощаем мы своим врагам.",
    "Твои все дивные дела,\nТвоё и царство, Властелин.\nТебе и слава, и хвала\nВо веки вечные! Аминь."
  ],
  "o": [
    {
      "w": 0,
      "p": [
        [2, 11],
        [1, 9],
        [2, 11],
        [1, 4, 10]
      ],
      "c": 0,
      "t": 0,
      "s": "one",
      "m": 1
    },
    {
      "w": 1,
      "p": [
        [1, 10],
        [1, 10],
        [1, 10],
        [2, 5, 10]
      ],
      "c": 0,
      "t": 1,
      "s": " one",
      "m": 0
    },
    {
      "w": 2,
      "p": [
        [1, 10],
        [3, 12],
        [2, 12],
        [2, 5, 11]
      ],
      "c": 0,
      "t": 2,
      "s": "one",
      "m": 0
    },
    {
      "w": 4,
      "p": [
        [2, 10],
        [1, 11],
        [2, 11],
        [1, 4, 10]
      ],
      "c": 0,
      "t": 3,
      "s": " one",
      "m": 0
    },
    {
      "w": 5,
      "p": [
        [1, 10],
        [1, 10],
        [1, 11],
        [2, 5, 10]
      ],
      "t": 4,
      "s": "one",
      "c": 0,
      "r": { "2-3": 2 }
    }
  ],
  "a": "https://holychords.pro/uploads/music/20220401/20220401170806.mp3",
  "m": 1762405896149,
  "al": "1~20220401//170806.mp3"
}
