{
  "w": 1680259720965,
  "n": "Быть ближе к Тебе",
  "al": "1~20200701//164457_50.mp3",
  "t": [
    "Присутствие Твоё так ценно для меня,\nНет лучше ничего, чем знать, что любишь Ты меня\nНет лучше ничего, чем знать, что Ты со мной\nИ то, что навсегда мы связаны с Тобой",
    "Быть ближе к Тебе ещё на шаг,\nБыть ближе к Тебе ещё на миг,\nБыть ближе к Тебе на расстояние\nДлиною в жизнь",
    "Пусть дни летят как миг, а годы как вода,\nМир пред Тобой как пыль и легче сна Земля...\nПусть времени поток куда-то вдаль спешит -\nЕму не обогнать порыв моей души:"
  ],
  "c": [
    "Cm D# Gm A",
    "Gm D# F Dm\nGm D# F Dm\nD# A/D Cm\nD# A/D Cm A/D D#",
    "Cm D# Gm A\nCm D# Gm A\nCm D# Gm A\nCm D# Gm"
  ],
  "o": [
    { "w": 0, "s": "enter", "c": 0 },
    {
      "w": 1,
      "t": 0,
      "s": "one",
      "c": 1,
      "p": [
        [1, 6, 10, 16],
        [2, 7, 15, 21],
        [2, 15, 19],
        [2, 8, 14, 17, 18]
      ]
    },
    {
      "w": 2,
      "t": 1,
      "s": "two",
      "c": 2,
      "p": [
        [2, 7, 10, 14],
        [2, 7, 10, 14],
        [2, 7, 11, 13],
        [-2, 1, 5]
      ]
    },
    {
      "w": 3,
      "t": 2,
      "s": "one",
      "c": 1,
      "p": [
        [2, 9, 13, 19],
        [2, 9, 13, 19],
        [2, 13, 16],
        [-2, 1, 7, 13, 16]
      ]
    },
    { "a": 2, "w": 4, "r": 2 }
  ]
}
