{
  "w": 1698065078262,
  "n": "Достоин Ты хвалы",
  "al": "1~20210208~~130216.mp3",
  "t": [
    "Ты взял мой крест тогда\nи принял смерть,\nЧтобы жил я в свободе\nВсю жизнь Тебе отдам,\nХочу воспеть\nТвою благость вовеки, Бог",
    "Достоин Ты один, Иисус.\nЧести и хвалы достоин только Ты.\nДостоин Ты один, Иисус.\nЧести и хвалы достоин только Ты.",
    "Я не стыжусь теперь,\nВ любви Твоей\nнаходясь несомненно!\nДаёшь вновь милость мне,\nХочу воспеть\nТвою благость вовеки, Бог.",
    "Возвеличен будь Ты на небе,\nизливая славу здесь\nТы принять достоин честь,\nТвоё имя выше всех\nВозвеличен будь Ты на небе,\nизливая славу здесь\nТы принять достоин честь,\nТвоё имя выше всех"
  ],
  "c": [
    "Hm D G A",
    "D A\nD/F# G\nAsus4 A\nD A\nD/F# G\nAsus4 A",
    "G Hm A\nD/F# Hm\nG Hm A\nD/F# Hm",
    "G\nEm\nHm\nA D/F#\nG\nEm\nHm\nA D/F#"
  ],
  "o": [
    { "w": 0, "c": 0, "k": 15 },
    {
      "w": 1,
      "t": 0,
      "c": 1,
      "p": [
        [-1, 6],
        [2, 5],
        [3, 9],
        [-1, 4],
        [-1, 4],
        [3, 7]
      ],
      "k": 39
    },
    {
      "w": 2,
      "t": 1,
      "c": 2,
      "r": 2,
      "p": [
        [1, 7, 11],
        [6, 15],
        [1, 7, 11],
        [6, 15]
      ],
      "k": 94
    },
    {
      "w": 3,
      "t": 2,
      "c": 1,
      "p": [
        [-1, 8],
        [-1, 5],
        [2, 6],
        [-1, 5],
        [-1, 4],
        [3, 7]
      ],
      "k": 39
    },
    { "w": 5, "a": 2, "r": 2 },
    { "w": 6, "t": 3, "c": 3, "r": 2, "p": [[3], [2], [3], [3, 9], [2], [2], [3], [3, 9]], "k": 31 },
    { "w": 7, "a": 2, "r": 2 }
  ]
}
