{
  "w": 1702735664164,
  "n": "Ты родился в этот мир",
  "bpm": 130,
  "d": 4,
  "al": "1~20200701//164137_18.mp3",
  "t": [
    "Вся земля полна славы и хвалы\nЛюбовь Отца нам явилась в Сыне\nИ зажглась в небе яркая звезда\nОна, мой друг, светит ярко и доныне",
    "Иисус! Иисус!",
    "Ты родился в этот мир\nЧтобы жизнь мне дать\nЧтоб всегда со мною быть\nСпасителем мне стать\nТы любовию Своей\nИзменил меня,\nизменил весь этот мир\nИисус! Мой Иисус!",
    "Подними к небу руки и тогда,\nЛьётся пусть слава и хвала Иисусу,\nЛикуй Земля, ведь открыты Небеса,\nРодился Царь и грех мира разрушен"
  ],
  "c": [
    "D Gmaj7\nD Gmaj7 A\nD Gmaj7\nD Gmaj7 A",
    "Em D A Em D A",
    "G A\nF#m7 Hm\nG A\nF#/A# Hm\nG A\nF#/A#\nHm A G\nA",
    "E H F#m E H/D# F#m A\nC#m H A F#m E H/D# H",
    "D G A D G A"
  ],
  "o": [
    { "w": 8, "c": 4, "k": 15 },
    {
      "w": 0,
      "t": 0,
      "c": 0,
      "p": [
        [0, 8],
        [1, 9, 13],
        [0, 9],
        [1, 10, 16]
      ],
      "k": 39
    },
    {
      "w": 1,
      "t": 1,
      "c": 1,
      "p": [
        [0, 1, 2, 4, 5, 6],
        [0, 1, 2]
      ],
      "k": 72
    },
    { "w": 2, "t": 2, "c": 2, "p": [[3, 10], [3, 7], [3, 10], [1, 7], [3, 8], [2], [2, 7, 9], [4]], "k": 94 },
    {
      "w": 3,
      "t": 3,
      "c": 0,
      "p": [
        [0, 8],
        [0, 8, 15],
        [1, 9],
        [1, 10, 14]
      ],
      "k": 39
    },
    { "a": 1, "w": 4 },
    { "a": 2, "w": 5, "r": 2 },
    { "w": 6, "c": 3, "f": { "md": 2 }, "v": 0, "k": 60 },
    { "w": 7, "a": 2, "r": 2, "v": 0 }
  ]
}
