{
  "n": "Иона, Иона, далеко от дома",
  "w": 1721505316303,
  "t": [
    "Иона, Иона, далеко от дома,\nУбегал от Бога по морям,\nА с Богом не играют, Он ветром управляет,\nИону Он качает на больших волнах.",
    "Но, ты не спрячешься\nи не скроешься\nот любви Его! О-о-о\nНет, не спрячешься\nи не скроешься\nот любви Его!",
    "Иона, Иона, далеко от дома,\nВспоминает Бога на морских волнах,\nА Бог всё продолжает, Иону кит глотает,\nИона понимает, что всё пошло не так.",
    "Иона, Иона, на глубинах моря\nНачинает к Богу голосом взывать.\nА Бог ведь отвечает - Иону отпускает.\nИона начинает это понимать.",
    "Что ты не спрячешься\nи не скроешься\nот любви Его! О-о-о\nНет, не спрячешься\nи не скроешься\nот любви Его!",
    "Дети, дети, не шутите с Богом,\nСловом Его держится небо и земля.\nИ на горе высокой, и даже в преисподней\nМожет вас найти Его верная Рука."
  ],
  "c": ["A D A7/C#\nH7 Hm7\nA D A7/C#\nH Hm A", "D\nA\nE F#m\nD\nA\nE .H7..Dm...A"],
  "o": [
    {
      "w": 0,
      "t": 0,
      "s": "one",
      "c": 0,
      "p": [
        [1, 7, 14],
        [0, 12],
        [3, 14, 19],
        [1, 10, 16]
      ]
    },
    { "w": 1, "t": 1, "s": "two", "c": 1, "p": [[2], [0], [-1, 6], [0], [0], [-1, 6]], "r": { "5:1-5": 3 } },
    {
      "w": 2,
      "t": 2,
      "s": "one",
      "c": 0,
      "p": [
        [1, 7, 14],
        [0, 8],
        [2, 12, 18],
        [1, 11, 18]
      ]
    },
    { "w": 3, "a": 1 },
    {
      "w": 4,
      "t": 3,
      "s": "one",
      "c": 0,
      "p": [
        [1, 8, 14],
        [0, 9],
        [2, 13, 18],
        [1, 9, 14]
      ]
    },
    { "w": 5, "t": 4, "s": "two", "c": 1, "p": [[2], [0], [-1, 6], [0], [0], [-1, 6]], "r": { "5:1-5": 3 } },
    {
      "w": 6,
      "t": 5,
      "s": "one",
      "c": 0,
      "p": [
        [0, 6, 13],
        [0, 10],
        [2, 13, 19],
        [0, 11, 16]
      ]
    },
    { "w": 7, "a": 1, "r": { ".": 2, "5:1-5": 3 } }
  ],
  "p": 0,
  "l": 0,
  "m": 1762405896168
}
