{
  "w": 1730625128177,
  "n": "Путь к Голгофе далёк",
  "nl": [
    {
      "0": "457 -135 -134 -135",
      "1": "246 -135 -135 -123",
      "2": "35 -146 -1357 -134",
      "6": "357 -135 -1357 -146",
      "10": "357 -147 -1357 -135"
    }
  ],
  "al": "1~20190917~~183518100.mp3",
  "t": [
    "путь к Голгофе далёк, Кровь стекала с чела,\nсколько мук и страданий во взоре...\nИисус дорогой умирал на кресте,\nпринял всё- и страданья, и горе.",
    "никогда не смогу я забыть этот крест,\nОн стоит между небом, землёю.\nСвоей смертью Христос примирил нас с Творцом,\nискупил драгоценною Кровью.",
    "о, услышь, человек, голос песни моей,\nчто ты медлишь, мой друг, что ты ждёшь?\nчем ты платишь Ему за божественный дар,\nза пролитую Кровь что даёшь?",
    "дар земли, свет зари, радость дней впереди-\nдля тебя это создал Господь.\nОн зовёт: \"О, приди!\"- мимо, друг, не пройди,\nв Нём ты счастье, покой обретёшь.",
    "дай, Господь, мне понять тайну вечной любви,\nтой, что Ты нам на землю принёс.\nи смогу я спокойно и твёрдо идти\nпо земле среди бурь, среди слёз."
  ],
  "c": ["Cm D#\nFm G Cm-G\nCm D#\nFm G Cm-C", "G# A# Gm Cm\nFm G Cm\nG# A# Gm Cm\nFm G Cm"],
  "o": [
    {
      "w": 0,
      "t": 0,
      "c": 0,
      "p": [
        [3, 13],
        [3, 8, 13],
        [2, 10],
        [3, 9, 14]
      ],
      "k": 39
    },
    {
      "w": 1,
      "t": 1,
      "c": 1,
      "p": [
        [2, 7, 12, 17],
        [3, 8, 12],
        [3, 7, 11, 17],
        [2, 6, 10]
      ],
      "k": 94
    },
    {
      "w": 2,
      "t": 2,
      "c": 0,
      "p": [
        [3, 12],
        [4, 9, 15],
        [4, 13],
        [3, 7, 12]
      ],
      "k": 39
    },
    {
      "w": 6,
      "t": 3,
      "c": 1,
      "p": [
        [3, 8, 13, 17],
        [3, 8, 12],
        [3, 8, 13, 18],
        [5, 9, 13]
      ],
      "k": 94
    },
    {
      "w": 10,
      "t": 4,
      "c": 0,
      "p": [
        [3, 13],
        [4, 10, 14],
        [3, 13],
        [3, 8, 13]
      ],
      "k": 39
    },
    { "w": 14, "a": 1 }
  ]
}
